id_informations/Armazenamento.py
id_informations/Consulta.py
id_informations/Interacao.py
id_informations/__init__.py
id_informations-0.0.1.dist-info/LICENSE.txt
id_informations-0.0.1.dist-info/METADATA
id_informations-0.0.1.dist-info/WHEEL
id_informations-0.0.1.dist-info/top_level.txt
id_informations-0.0.1.dist-info/RECORD
