Metadata-Version: 2.1
Name: id-informations
Version: 0.0.1
Summary: Pacote python para entrar com informacoes de identificacao
Home-page: https://github.com/VLR03
Author: Vitor Longhi Ramoa
Author-email: vitorlr03@gmail.com
License: MIT License
Keywords: Pacote
Platform: UNKNOWN
License-File: LICENSE.txt
